finger_sdk/__init__.py
finger_sdk/client.py
finger_sdk/ida_func.py
finger_sdk-0.1.dist-info/DESCRIPTION.rst
finger_sdk-0.1.dist-info/METADATA
finger_sdk-0.1.dist-info/RECORD
finger_sdk-0.1.dist-info/WHEEL
finger_sdk-0.1.dist-info/metadata.json
finger_sdk-0.1.dist-info/top_level.txt
